didlite/__init__.py
didlite/core.py
didlite/jws.py
didlite/keystore.py
didlite-0.2.5.dist-info/licenses/LICENSE
didlite-0.2.5.dist-info/METADATA
didlite-0.2.5.dist-info/WHEEL
didlite-0.2.5.dist-info/top_level.txt
didlite-0.2.5.dist-info/RECORD
