Metadata-Version: 2.4
Name: didlite
Version: 0.2.5
Summary: Zero-dependency-bloat Python library for W3C Decentralized Identifiers (DIDs) using Ed25519 keys
Author-email: Jon DePalma <jon@jondepalma.com>
License: Apache-2.0
Project-URL: Homepage, https://github.com/jondepalma/didlite-pkg
Project-URL: Documentation, https://github.com/jondepalma/didlite-pkg#readme
Project-URL: Repository, https://github.com/jondepalma/didlite-pkg
Project-URL: Issues, https://github.com/jondepalma/didlite-pkg/issues
Project-URL: Changelog, https://github.com/jondepalma/didlite-pkg/blob/main/CHANGELOG.md
Project-URL: Security, https://github.com/jondepalma/didlite-pkg/blob/main/.github/SECURITY.md
Keywords: did,decentralized-identity,ed25519,jwt,jws,iot,edge,ai-agents
Classifier: Development Status :: 4 - Beta
Classifier: Intended Audience :: Developers
Classifier: Programming Language :: Python :: 3
Classifier: Programming Language :: Python :: 3.9
Classifier: Programming Language :: Python :: 3.10
Classifier: Programming Language :: Python :: 3.11
Classifier: Programming Language :: Python :: 3.12
Classifier: Topic :: Security :: Cryptography
Classifier: Topic :: Software Development :: Libraries :: Python Modules
Requires-Python: >=3.9
License-File: LICENSE
Requires-Dist: pynacl>=1.5.0
Requires-Dist: py-multibase>=1.0.0
Requires-Dist: cryptography>=41.0.0
Provides-Extra: test
Requires-Dist: pytest>=7.0.0; extra == "test"
Requires-Dist: pytest-cov>=4.0.0; extra == "test"
Requires-Dist: authlib>=1.0.0; extra == "test"
Requires-Dist: hypothesis>=6.0.0; extra == "test"
Dynamic: license-file
